kuyruk_sentry.py
Kuyruk_Sentry-1.1.5.dist-info/LICENSE
Kuyruk_Sentry-1.1.5.dist-info/METADATA
Kuyruk_Sentry-1.1.5.dist-info/WHEEL
Kuyruk_Sentry-1.1.5.dist-info/entry_points.txt
Kuyruk_Sentry-1.1.5.dist-info/top_level.txt
Kuyruk_Sentry-1.1.5.dist-info/RECORD
