Metadata-Version: 2.1
Name: Kuyruk-Sentry
Version: 1.1.5
Summary: Sends exceptions in Kuyruk workers to Sentry.
Home-page: https://github.com/cenkalti/kuyruk-sentry
Author: Cenk Altı
Author-email: cenkalti@gmail.com
Keywords: kuyruk sentry
Classifier: Development Status :: 5 - Production/Stable
Classifier: License :: OSI Approved :: MIT License
Classifier: Operating System :: OS Independent
Classifier: Programming Language :: Python
Classifier: Programming Language :: Python :: 2.7
Classifier: Programming Language :: Python :: 3
Classifier: Topic :: Software Development :: Object Brokering
Classifier: Topic :: System :: Distributed Computing
License-File: LICENSE
Requires-Dist: kuyruk >=8.0.0
Requires-Dist: sentry-sdk >=0.15.1
